CHANGES.md
LICENSE.AGPL.md
LICENSE.md
MANIFEST.in
README.md
VERSION
setup.cfg
setup.py
bin/rc.socksify
bin/rc.socksify.bak
src/rc/__init__.py
src/rc.rfc.1928.egg-info/PKG-INFO
src/rc.rfc.1928.egg-info/SOURCES.txt
src/rc.rfc.1928.egg-info/dependency_links.txt
src/rc.rfc.1928.egg-info/namespace_packages.txt
src/rc.rfc.1928.egg-info/not-zip-safe
src/rc.rfc.1928.egg-info/requires.txt
src/rc.rfc.1928.egg-info/top_level.txt
src/rc/rfc1928/SDIST
src/rc/rfc1928/VERSION
src/rc/rfc1928/__init__.py
src/rc/rfc1928/rfc_1928.py
src/rc/rfc1928/rfc_1928.py.bak